{
	"$schema" : "https://aka.ms/winget-packages.schema.2.0.json",
	"CreationDate" : "2021-10-19T02:28:22.903-00:00",
	"Sources" : 
	[
		{
			"Packages" : 
			[
				{
					"PackageIdentifier" : "AgileBits.1Password"
				},
				{
					"PackageIdentifier" : "DeepL.DeepL"
				},
				{
					"PackageIdentifier" : "Discord.Discord"
				},
				{
					"PackageIdentifier" : "Docker.DockerDesktop"
				},
				{
					"PackageIdentifier" : "Dropbox.Dropbox"
				},
				{
					"PackageIdentifier" : "Git.Git"
				},
				{
					"PackageIdentifier" : "Microsoft.Edge"
				},
				{
					"PackageIdentifier" : "Microsoft.WindowsTerminal"
				},
				{
					"PackageIdentifier" : "Mozilla.Firefox"
				},
				{
					"PackageIdentifier" : "QNAP.QfinderPro"
				},
				{
					"PackageIdentifier" : "Spotify.Spotify"
				},
				{
					"PackageIdentifier" : "SlackTechnologies.Slack"
				},
				{
					"PackageIdentifier" : "Google.ChromeRemoteDesktop"
				},
				{
					"PackageIdentifier" : "VideoLAN.VLC"
				},
				{
					"PackageIdentifier" : "Amazon.SAM-CLI"
				},
				{
					"PackageIdentifier" : "Python.Python.3"
				},
				{
					"PackageIdentifier" : "7zip.7zip"
				},
				{
					"PackageIdentifier" : "Telegram.TelegramDesktop"
				},
				{
					"PackageIdentifier" : "Microsoft.VisualStudioCode"
				},
				{
					"PackageIdentifier" : "Google.Chrome"
				},
				{
					"PackageIdentifier" : "Google.JapaneseIME"
				},
				{
					"PackageIdentifier" : "Amazon.AWSCLI"
				},
				{
					"PackageIdentifier" : "Nvidia.GeForceExperience"
				}
			],
			"SourceDetails" : 
			{
				"Argument" : "https://winget.azureedge.net/cache",
				"Identifier" : "Microsoft.Winget.Source_8wekyb3d8bbwe",
				"Name" : "winget",
				"Type" : "Microsoft.PreIndexed.Package"
			}
		}
	],
	"WinGetVersion" : "1.1.12653"
}